[
  {
    "id": "107",
    "title": "Markdown写作指南",
    "date": "2026-06-09 10:00",
    "last_modified": "2026-06-09 10:00",
    "author": "Admin",
    "category": ["技术"],
    "tags": ["Markdown","教程"],
    "desc": "一篇使用Markdown格式编写的示例文章，展示MD文件支持功能。"
  },
  {
    "id": "106",
    "title": "Hello world!",
    "date": "2025-12-29 17:55",
    "last_modified": "2025-12-29 17:55",
    "author": "Admin",
    "category": ["Demo"],
    "tags": ["Demo"],
    "desc": "Hello world!"
  },
  {
    "id": "104",
    "title": "pixiv",
    "date": "2025-12-26 08:59",
    "last_modified": "2025-12-26 08:59",
    "author": "Lamb",
    "category": ["Demo"],
    "tags": ["Demo"],
    "type": "gallery"
  },
  {
    "id": "103",
    "title": "代码高亮与排版组件演示",
    "date": "2025-12-12 13:09",
    "last_modified": "2025-12-12 17:36",
    "author": "Admin",
    "category": ["Demo"],
    "tags": ["Demo"],
    "desc": "代码高亮与排版组件演示"
  },
  {
    "id": "102",
    "title": "周五的公园与猫",
    "date": "2025-11-22 10:30",
    "last_modified": "2025-11-22 10:32",
    "author": "Anonymous",
    "category": ["说说","生活"],
    "tags": ["猫"],
    "type": "note",
    "content": "今天天气真不错，在公园里看到了一只非常慵懒的猫。生活就该偶尔停下来发发呆。\n\n![猫](https://images.unsplash.com/photo-1514888286974-6c03e2ca1dba?q=80&w=1000&auto=format&fit=crop)\n\n拍完照它就跑了，哈哈。\n\n![猫2](https://images.unsplash.com/photo-1573865526739-10659fec78a5?q=80&w=1000&auto=format&fit=crop)\n\n晚上准备去吃顿火锅庆祝一下周五！"
  },
  {
    "id": "101",
    "title": "月下独酌：李白诗中的孤独与自由",
    "date": "2025-11-21 13:09",
    "last_modified": "2025-11-21 13:09",
    "author": "Anonymous",
    "category": ["闲谈\"]"],
    "tags": ["书评\"]"],
    "desc": "品读李白《月下独酌》，探寻诗仙在孤独中寻得的自由境界。",
    "image": "https://images.unsplash.com/photo-1506905925346-21bda4d32df4?q=80&w=1000&auto=format&fit=crop"
  }
]